tests/__init__.py
tests/test_cloudpy.py
xoxzo/__init__.py
xoxzo/cloudpy/__init__.py
xoxzo/cloudpy/cloudpy.py
xoxzo.cloudpy-0.2.dist-info/DESCRIPTION.rst
xoxzo.cloudpy-0.2.dist-info/METADATA
xoxzo.cloudpy-0.2.dist-info/RECORD
xoxzo.cloudpy-0.2.dist-info/WHEEL
xoxzo.cloudpy-0.2.dist-info/metadata.json
xoxzo.cloudpy-0.2.dist-info/top_level.txt
