Metadata-Version: 2.0
Name: xoxzo.cloudpy
Version: 0.2
Summary: Xoxzo Public API library
Home-page: https://github.com/xoxzo/xoxzo.cloudpy
Author: Xoxzo Inc.
Author-email: help@xoxzo.com
License: MIT
Keywords: xoxzo telephony api
Platform: UNKNOWN
Requires-Dist: requests (>=2.9.1)
